TFLIGHT/TFLIGHT.srcs/sources_1/new/Translator.v
`timescale 1ns / 1ps

module decoder(in,out);
    input [7:0] in;
    output reg [7:0] out = 0;

    reg [7:0] prev_in = 0;
    
    reg [15:0] tmp = 0;
    integer i = 0;
    always@(*)begin
        if(prev_in[7:0] != in[7:0])begin
            if(in == 8'b10101010 || in == 8'hff) begin     //阻塞或不显示的时候不进行译码
                out = in;
                prev_in = in;
            end else begin
                out = in;
                tmp = {8'b0,in};
                prev_in = in;
                i = 0;        
                for(i = 0; i < 8; i = i + 1)begin
                    if(tmp[15:12] > 4) tmp[15:12] = tmp[15:12] + 3;
                    if(tmp[11:8] > 4) tmp[11:8] = tmp[11:8] + 3;
                    tmp = tmp << 1;
                end
                out = tmp[15:8];
            end
        end
    end
endmodule

TFLIGHT/TFLIGHT.srcs/sim_1/new/decoder_simu.v
`timescale 1ns / 1ps
`include "/Users/mrx/Library/CloudStorage/OneDrive-个人/programing/digitcircuit/tmpt/dc_1/TFLIGHT/TFLIGHT.srcs/sources_1/new/Translator.v"

module decoder_simu();
    
    reg [7:0] bin;
    wire [7:0] ans;

    decoder utt(bin,ans);
    integer i;

    initial begin
        $display("start");                  
        $dumpfile("decoder_wave.vcd");              
        $dumpvars(0, decoder_simu);

        bin = 8'hff;
        #20
        bin = 8'b10101010;
        #20
        bin = 8'd0;
        for(i = 0;i < 300; i = i + 1) begin
            #20
            bin = i;
        end
        $finish;                      // 6000个单位时间后结束模拟
    end

    
endmodule

TFLIGHT/TFLIGHT.sim/sim_1/behav/xsim/decoder_wave.vcd
$date
   Fri Feb 24 13:28:07 2023
$end
$version
  2020.1
$end
$timescale
  1ps
$end
$scope module decoder_simu $end
$var reg 8 ! bin [7:0] $end
$var wire 8 " ans [7:0] $end
$var integer 32 # i $end
$scope module utt $end
$var wire 8 $ in [7:0] $end
$var reg 8 % out [7:0] $end
$var reg 8 & prev_in [7:0] $end
$var reg 16 ' tmp [15:0] $end
$var integer 32 ( i $end
$upscope $end
$upscope $end
$enddefinitions $end
#0
$dumpvars
b11111111 !
b11111111 "
bx #
b11111111 $
b11111111 %
b11111111 &
b0 '
b0 (
$end
#20000
b10101010 !
b10101010 "
b10101010 $
b10101010 %
b10101010 &
#40000
b0 !
b0 "
b0 #
b0 $
b0 %
b0 &
b0 '
b1000 (
#60000
b0 !
b1 #
#80000
b1 !
b1 "
b10 #
b1 $
b1 %
b1 &
b100000000 '
b1000 (
#100000
b10 !
b10 "
b11 #
b10 $
b10 %
b10 &
b1000000000 '
b1000 (
#120000
b11 !
b11 "
b100 #
b11 $
b11 %
b11 &
b1100000000 '
b1000 (
#140000
b100 !
b100 "
b101 #
b100 $
b100 %
b100 &
b10000000000 '
b1000 (
#160000
b101 !
b101 "
b110 #
b101 $
b101 %
b101 &
b10100000000 '
b1000 (
#180000
b110 !
b110 "
b111 #
b110 $
b110 %
b110 &
b11000000000 '
b1000 (
#200000
b111 !
b111 "
b1000 #
b111 $
b111 %
b111 &
b11100000000 '
b1000 (
#220000
b1000 !
b1000 "
b1001 #
b1000 $
b1000 %
b1000 &
b100000000000 '
b1000 (
#240000
b1001 !
b1001 "
b1010 #
b1001 $
b1001 %
b1001 &
b100100000000 '
b1000 (
#260000
b1010 !
b10000 "
b1011 #
b1010 $
b10000 %
b1010 &
b1000000000000 '
b1000 (
#280000
b1011 !
b10001 "
b1100 #
b1011 $
b10001 %
b1011 &
b1000100000000 '
b1000 (
#300000
b1100 !
b10010 "
b1101 #
b1100 $
b10010 %
b1100 &
b1001000000000 '
b1000 (
#320000
b1101 !
b10011 "
b1110 #
b1101 $
b10011 %
b1101 &
b1001100000000 '
b1000 (
#340000
b1110 !
b10100 "
b1111 #
b1110 $
b10100 %
b1110 &
b1010000000000 '
b1000 (
#360000
b1111 !
b10101 "
b10000 #
b1111 $
b10101 %
b1111 &
b1010100000000 '
b1000 (
#380000
b10000 !
b10110 "
b10001 #
b10000 $
b10110 %
b10000 &
b1011000000000 '
b1000 (
#400000
b10001 !
b10111 "
b10010 #
b10001 $
b10111 %
b10001 &
b1011100000000 '
b1000 (
#420000
b10010 !
b11000 "
b10011 #
b10010 $
b11000 %
b10010 &
b1100000000000 '
b1000 (
#440000
b10011 !
b11001 "
b10100 #
b10011 $
b11001 %
b10011 &
b1100100000000 '
b1000 (
#460000
b10100 !
b100000 "
b10101 #
b10100 $
b100000 %
b10100 &
b10000000000000 '
b1000 (
#480000
b10101 !
b100001 "
b10110 #
b10101 $
b100001 %
b10101 &
b10000100000000 '
b1000 (
#500000
b10110 !
b100010 "
b10111 #
b10110 $
b100010 %
b10110 &
b10001000000000 '
b1000 (
#520000
b10111 !
b100011 "
b11000 #
b10111 $
b100011 %
b10111 &
b10001100000000 '
b1000 (
#540000
b11000 !
b100100 "
b11001 #
b11000 $
b100100 %
b11000 &
b10010000000000 '
b1000 (
#560000
b11001 !
b100101 "
b11010 #
b11001 $
b100101 %
b11001 &
b10010100000000 '
b1000 (
#580000
b11010 !
b100110 "
b11011 #
b11010 $
b100110 %
b11010 &
b10011000000000 '
b1000 (
#600000
b11011 !
b100111 "
b11100 #
b11011 $
b100111 %
b11011 &
b10011100000000 '
b1000 (
#620000
b11100 !
b101000 "
b11101 #
b11100 $
b101000 %
b11100 &
b10100000000000 '
b1000 (
#640000
b11101 !
b101001 "
b11110 #
b11101 $
b101001 %
b11101 &
b10100100000000 '
b1000 (
#660000
b11110 !
b110000 "
b11111 #
b11110 $
b110000 %
b11110 &
b11000000000000 '
b1000 (
#680000
b11111 !
b110001 "
b100000 #
b11111 $
b110001 %
b11111 &
b11000100000000 '
b1000 (
#700000
b100000 !
b110010 "
b100001 #
b100000 $
b110010 %
b100000 &
b11001000000000 '
b1000 (
#720000
b100001 !
b110011 "
b100010 #
b100001 $
b110011 %
b100001 &
b11001100000000 '
b1000 (
#740000
b100010 !
b110100 "
b100011 #
b100010 $
b110100 %
b100010 &
b11010000000000 '
b1000 (
#760000
b100011 !
b110101 "
b100100 #
b100011 $
b110101 %
b100011 &
b11010100000000 '
b1000 (
#780000
b100100 !
b110110 "
b100101 #
b100100 $
b110110 %
b100100 &
b11011000000000 '
b1000 (
#800000
b100101 !
b110111 "
b100110 #
b100101 $
b110111 %
b100101 &
b11011100000000 '
b1000 (
#820000
b100110 !
b111000 "
b100111 #
b100110 $
b111000 %
b100110 &
b11100000000000 '
b1000 (
#840000
b100111 !
b111001 "
b101000 #
b100111 $
b111001 %
b100111 &
b11100100000000 '
b1000 (
#860000
b101000 !
b1000000 "
b101001 #
b101000 $
b1000000 %
b101000 &
b100000000000000 '
b1000 (
#880000
b101001 !
b1000001 "
b101010 #
b101001 $
b1000001 %
b101001 &
b100000100000000 '
b1000 (
#900000
b101010 !
b1000010 "
b101011 #
b101010 $
b1000010 %
b101010 &
b100001000000000 '
b1000 (
#920000
b101011 !
b1000011 "
b101100 #
b101011 $
b1000011 %
b101011 &
b100001100000000 '
b1000 (
#940000
b101100 !
b1000100 "
b101101 #
b101100 $
b1000100 %
b101100 &
b100010000000000 '
b1000 (
#960000
b101101 !
b1000101 "
b101110 #
b101101 $
b1000101 %
b101101 &
b100010100000000 '
b1000 (
#980000
b101110 !
b1000110 "
b101111 #
b101110 $
b1000110 %
b101110 &
b100011000000000 '
b1000 (
#1000000
b101111 !
b1000111 "
b110000 #
b101111 $
b1000111 %
b101111 &
b100011100000000 '
b1000 (
