TFLIGHT/TFLIGHT.srcs/sources_1/new/Translator.v
`timescale 1ns / 1ps

module decoder(in,out);
    input [7:0] in;
    output reg [7:0] out = 0;

    reg [7:0] prev_in = 0;
    
    reg [15:0] tmp = 0;
    integer i = 0;
    always@(*)begin
        if(prev_in[7:0] != in[7:0])begin
            if(in == 8'b10101010 || in == 8'hff) begin     //阻塞或不显示的时候不进行译码
                out = in;
                prev_in = in;
            end else begin
                out = in;
                tmp = {8'b0,in};
                prev_in = in;
                i = 0;        
                for(i = 0; i < 8; i = i + 1)begin
                    if(tmp[15:12] > 4) tmp[15:12] = tmp[15:12] + 3;
                    if(tmp[11:8] > 4) tmp[11:8] = tmp[11:8] + 3;
                    tmp = tmp << 1;
                end
                out = tmp[15:8];
            end
        end
    end
endmodule

TFLIGHT/TFLIGHT.srcs/sim_1/new/decoder_simu.v
`timescale 1ns / 1ps
`include "/Users/mrx/Library/CloudStorage/OneDrive-个人/programing/digitcircuit/tmpt/dc_1/TFLIGHT/TFLIGHT.srcs/sources_1/new/Translator.v"

module decoder_simu();
    
    reg [7:0] bin;
    wire [7:0] ans;

    decoder utt(bin,ans);
    integer i;

    initial begin
        $display("start");                  
        $dumpfile("decoder_wave.vcd");              
        $dumpvars(0, decoder_simu);

        bin = 8'hff;
        #20
        bin = 8'b10101010;
        #20
        bin = 8'd0;
        for(i = 0;i < 300; i = i + 1) begin
            #20
            bin = i;
        end
        $finish;                      // 6000个单位时间后结束模拟
    end

    
endmodule

TFLIGHT/TFLIGHT.srcs/sim_1/new/decoder_wave.vcd
$date
	Fri Feb 24 01:07:42 2023
$end
$version
	Icarus Verilog
$end
$timescale
	1ps
$end
$scope module decoder_simu $end
$var wire 8 ! ans [7:0] $end
$var reg 8 " bin [7:0] $end
$var integer 32 # i [31:0] $end
$scope module utt $end
$var wire 8 $ in [7:0] $end
$var reg 8 % out [7:0] $end
$var reg 8 & prev_in [7:0] $end
$var reg 16 ' tmp [15:0] $end
$var integer 32 ( i [31:0] $end
$upscope $end
$upscope $end
$enddefinitions $end
#0
$dumpvars
b0 (
b0 '
b11111111 &
b11111111 %
b11111111 $
bx #
b11111111 "
b11111111 !
$end
#20000
b10101010 &
b10101010 !
b10101010 %
b10101010 "
b10101010 $
#40000
b1000 (
b0 &
b0 !
b0 %
b0 #
b0 "
b0 $
#60000
b1 #
#80000
b1000 (
b1 &
b100000000 '
b1 !
b1 %
b10 #
b1 "
b1 $
#100000
b1000 (
b10 &
b1000000000 '
b10 !
b10 %
b11 #
b10 "
b10 $
#120000
b1000 (
b11 &
b1100000000 '
b11 !
b11 %
b100 #
b11 "
b11 $
#140000
b1000 (
b100 &
b10000000000 '
b100 !
b100 %
b101 #
b100 "
b100 $
#160000
b1000 (
b101 &
b10100000000 '
b101 !
b101 %
b110 #
b101 "
b101 $
#180000
b1000 (
b110 &
b11000000000 '
b110 !
b110 %
b111 #
b110 "
b110 $
#200000
b1000 (
b111 &
b11100000000 '
b111 !
b111 %
b1000 #
b111 "
b111 $
#220000
b1000 (
b1000 &
b100000000000 '
b1000 !
b1000 %
b1001 #
b1000 "
b1000 $
#240000
b1000 (
b1001 &
b100100000000 '
b1001 !
b1001 %
b1010 #
b1001 "
b1001 $
#260000
b1000 (
b1010 &
b1000000000000 '
b10000 !
b10000 %
b1011 #
b1010 "
b1010 $
#280000
b1000 (
b1011 &
b1000100000000 '
b10001 !
b10001 %
b1100 #
b1011 "
b1011 $
#300000
b1000 (
b1100 &
b1001000000000 '
b10010 !
b10010 %
b1101 #
b1100 "
b1100 $
#320000
b1000 (
b1101 &
b1001100000000 '
b10011 !
b10011 %
b1110 #
b1101 "
b1101 $
#340000
b1000 (
b1110 &
b1010000000000 '
b10100 !
b10100 %
b1111 #
b1110 "
b1110 $
#360000
b1000 (
b1111 &
b1010100000000 '
b10101 !
b10101 %
b10000 #
b1111 "
b1111 $
#380000
b1000 (
b10000 &
b1011000000000 '
b10110 !
b10110 %
b10001 #
b10000 "
b10000 $
#400000
b1000 (
b10001 &
b1011100000000 '
b10111 !
b10111 %
b10010 #
b10001 "
b10001 $
#420000
b1000 (
b10010 &
b1100000000000 '
b11000 !
b11000 %
b10011 #
b10010 "
b10010 $
#440000
b1000 (
b10011 &
b1100100000000 '
b11001 !
b11001 %
b10100 #
b10011 "
b10011 $
#460000
b1000 (
b10100 &
b10000000000000 '
b100000 !
b100000 %
b10101 #
b10100 "
b10100 $
#480000
b1000 (
b10101 &
b10000100000000 '
b100001 !
b100001 %
b10110 #
b10101 "
b10101 $
#500000
b1000 (
b10110 &
b10001000000000 '
b100010 !
b100010 %
b10111 #
b10110 "
b10110 $
#520000
b1000 (
b10111 &
b10001100000000 '
b100011 !
b100011 %
b11000 #
b10111 "
b10111 $
#540000
b1000 (
b11000 &
b10010000000000 '
b100100 !
b100100 %
b11001 #
b11000 "
b11000 $
#560000
b1000 (
b11001 &
b10010100000000 '
b100101 !
b100101 %
b11010 #
b11001 "
b11001 $
#580000
b1000 (
b11010 &
b10011000000000 '
b100110 !
b100110 %
b11011 #
b11010 "
b11010 $
#600000
b1000 (
b11011 &
b10011100000000 '
b100111 !
b100111 %
b11100 #
b11011 "
b11011 $
#620000
b1000 (
b11100 &
b10100000000000 '
b101000 !
b101000 %
b11101 #
b11100 "
b11100 $
#640000
b1000 (
b11101 &
b10100100000000 '
b101001 !
b101001 %
b11110 #
b11101 "
b11101 $
#660000
b1000 (
b11110 &
b11000000000000 '
b110000 !
b110000 %
b11111 #
b11110 "
b11110 $
#680000
b1000 (
b11111 &
b11000100000000 '
b110001 !
b110001 %
b100000 #
b11111 "
b11111 $
#700000
b1000 (
b100000 &
b11001000000000 '
b110010 !
b110010 %
b100001 #
b100000 "
b100000 $
#720000
b1000 (
b100001 &
b11001100000000 '
b110011 !
b110011 %
b100010 #
b100001 "
b100001 $
#740000
b1000 (
b100010 &
b11010000000000 '
b110100 !
b110100 %
b100011 #
b100010 "
b100010 $
#760000
b1000 (
b100011 &
b11010100000000 '
b110101 !
b110101 %
b100100 #
b100011 "
b100011 $
#780000
b1000 (
b100100 &
b11011000000000 '
b110110 !
b110110 %
b100101 #
b100100 "
b100100 $
#800000
b1000 (
b100101 &
b11011100000000 '
b110111 !
b110111 %
b100110 #
b100101 "
b100101 $
#820000
b1000 (
b100110 &
b11100000000000 '
b111000 !
b111000 %
b100111 #
b100110 "
b100110 $
#840000
b1000 (
b100111 &
b11100100000000 '
b111001 !
b111001 %
b101000 #
b100111 "
b100111 $
#860000
b1000 (
b101000 &
b100000000000000 '
b1000000 !
b1000000 %
b101001 #
b101000 "
b101000 $
#880000
b1000 (
b101001 &
b100000100000000 '
b1000001 !
b1000001 %
b101010 #
b101001 "
b101001 $
#900000
b1000 (
b101010 &
b100001000000000 '
b1000010 !
b1000010 %
b101011 #
b101010 "
b101010 $
#920000
b1000 (
b101011 &
b100001100000000 '
b1000011 !
b1000011 %
b101100 #
b101011 "
b101011 $
#940000
b1000 (
b101100 &
b100010000000000 '
b1000100 !
b1000100 %
b101101 #
b101100 "
b101100 $
#960000
b1000 (
b101101 &
b100010100000000 '
b1000101 !
b1000101 %
b101110 #
b101101 "
b101101 $
#980000
b1000 (
b101110 &
b100011000000000 '
b1000110 !
b1000110 %
b101111 #
b101110 "
b101110 $
#1000000
b1000 (
b101111 &
b100011100000000 '
b1000111 !
b1000111 %
b110000 #
b101111 "
b101111 $
#1020000
b1000 (
b110000 &
b100100000000000 '
b1001000 !
b1001000 %
b110001 #
b110000 "
b110000 $
#1040000
b1000 (
b110001 &
b100100100000000 '
b1001001 !
b1001001 %
b110010 #
b110001 "
b110001 $
#1060000
b1000 (
b110010 &
b101000000000000 '
b1010000 !
b1010000 %
b110011 #
b110010 "
b110010 $
#1080000
b1000 (
b110011 &
b101000100000000 '
b1010001 !
b1010001 %
b110100 #
b110011 "
b110011 $
#1100000
b1000 (
b110100 &
b101001000000000 '
b1010010 !
b1010010 %
b110101 #
b110100 "
b110100 $
#1120000
b1000 (
b110101 &
b101001100000000 '
b1010011 !
b1010011 %
b110110 #
b110101 "
b110101 $
#1140000
b1000 (
b110110 &
b101010000000000 '
b1010100 !
b1010100 %
b110111 #
b110110 "
b110110 $
#1160000
b1000 (
b110111 &
b101010100000000 '
b1010101 !
b1010101 %
b111000 #
b110111 "
b110111 $
#1180000
b1000 (
b111000 &
b101011000000000 '
b1010110 !
b1010110 %
b111001 #
b111000 "
b111000 $
#1200000
b1000 (
b111001 &
b101011100000000 '
b1010111 !
b1010111 %
b111010 #
b111001 "
b111001 $
#1220000
b1000 (
b111010 &
b101100000000000 '
b1011000 !
b1011000 %
b111011 #
b111010 "
b111010 $
#1240000
b1000 (
b111011 &
b101100100000000 '
b1011001 !
b1011001 %
b111100 #
b111011 "
b111011 $
#1260000
b1000 (
b111100 &
b110000000000000 '
b1100000 !
b1100000 %
b111101 #
b111100 "
b111100 $
#1280000
b1000 (
b111101 &
b110000100000000 '
b1100001 !
b1100001 %
b111110 #
b111101 "
b111101 $
#1300000
b1000 (
b111110 &
b110001000000000 '
b1100010 !
b1100010 %
b111111 #
b111110 "
b111110 $
#1320000
b1000 (
b111111 &
b110001100000000 '
b1100011 !
b1100011 %
b1000000 #
b111111 "
b111111 $
#1340000
b1000 (
b1000000 &
b110010000000000 '
b1100100 !
b1100100 %
b1000001 #
b1000000 "
b1000000 $
#1360000
b1000 (
b1000001 &
b110010100000000 '
b1100101 !
b1100101 %
b1000010 #
b1000001 "
b1000001 $
#1380000
b1000 (
b1000010 &
b110011000000000 '
b1100110 !
b1100110 %
b1000011 #
b1000010 "
b1000010 $
#1400000
b1000 (
b1000011 &
b110011100000000 '
b1100111 !
b1100111 %
b1000100 #
b1000011 "
b1000011 $
#1420000
b1000 (
b1000100 &
b110100000000000 '
b1101000 !
b1101000 %
b1000101 #
b1000100 "
b1000100 $
#1440000
b1000 (
b1000101 &
b110100100000000 '
b1101001 !
b1101001 %
b1000110 #
b1000101 "
b1000101 $
#1460000
b1000 (
b1000110 &
b111000000000000 '
b1110000 !
b1110000 %
b1000111 #
b1000110 "
b1000110 $
#1480000
b1000 (
b1000111 &
b111000100000000 '
b1110001 !
b1110001 %
b1001000 #
b1000111 "
b1000111 $
#1500000
b1000 (
b1001000 &
b111001000000000 '
b1110010 !
b1110010 %
b1001001 #
b1001000 "
b1001000 $
#1520000
b1000 (
b1001001 &
b111001100000000 '
b1110011 !
b1110011 %
b1001010 #
b1001001 "
b1001001 $
#1540000
b1000 (
b1001010 &
b111010000000000 '
b1110100 !
b1110100 %
b1001011 #
b1001010 "
b1001010 $
#1560000
b1000 (
b1001011 &
b111010100000000 '
b1110101 !
b1110101 %
b1001100 #
b1001011 "
b1001011 $
#1580000
b1000 (
b1001100 &
b111011000000000 '
b1110110 !
b1110110 %
b1001101 #
b1001100 "
b1001100 $
#1600000
b1000 (
b1001101 &
b111011100000000 '
b1110111 !
b1110111 %
b1001110 #
b1001101 "
b1001101 $
#1620000
b1000 (
b1001110 &
b111100000000000 '
b1111000 !
b1111000 %
b1001111 #
b1001110 "
b1001110 $
#1640000
b1000 (
b1001111 &
b111100100000000 '
b1111001 !
b1111001 %
b1010000 #
b1001111 "
b1001111 $
#1660000
b1000 (
b1010000 &
b1000000000000000 '
b10000000 !
b10000000 %
b1010001 #
b1010000 "
b1010000 $
#1680000
b1000 (
b1010001 &
b1000000100000000 '
b10000001 !
b10000001 %
b1010010 #
b1010001 "
b1010001 $
#1700000
b1000 (
b1010010 &
b1000001000000000 '
b10000010 !
b10000010 %
b1010011 #
b1010010 "
b1010010 $
#1720000
b1000 (
b1010011 &
b1000001100000000 '
b10000011 !
b10000011 %
b1010100 #
b1010011 "
b1010011 $
#1740000
b1000 (
b1010100 &
b1000010000000000 '
b10000100 !
b10000100 %
b1010101 #
b1010100 "
b1010100 $
#1760000
b1000 (
b1010101 &
b1000010100000000 '
b10000101 !
b10000101 %
b1010110 #
b1010101 "
b1010101 $
#1780000
b1000 (
b1010110 &
b1000011000000000 '
b10000110 !
b10000110 %
b1010111 #
b1010110 "
b1010110 $
#1800000
b1000 (
b1010111 &
b1000011100000000 '
b10000111 !
b10000111 %
b1011000 #
b1010111 "
b1010111 $
#1820000
b1000 (
b1011000 &
b1000100000000000 '
b10001000 !
b10001000 %
b1011001 #
b1011000 "
b1011000 $
#1840000
b1000 (
b1011001 &
b1000100100000000 '
b10001001 !
b10001001 %
b1011010 #
b1011001 "
b1011001 $
#1860000
b1000 (
b1011010 &
b1001000000000000 '
b10010000 !
b10010000 %
b1011011 #
b1011010 "
b1011010 $
#1880000
b1000 (
b1011011 &
b1001000100000000 '
b10010001 !
b10010001 %
b1011100 #
b1011011 "
b1011011 $
#1900000
b1000 (
b1011100 &
b1001001000000000 '
b10010010 !
b10010010 %
b1011101 #
b1011100 "
b1011100 $
#1920000
b1000 (
b1011101 &
b1001001100000000 '
b10010011 !
b10010011 %
b1011110 #
b1011101 "
b1011101 $
#1940000
b1000 (
b1011110 &
b1001010000000000 '
b10010100 !
b10010100 %
b1011111 #
b1011110 "
b1011110 $
#1960000
b1000 (
b1011111 &
b1001010100000000 '
b10010101 !
b10010101 %
b1100000 #
b1011111 "
b1011111 $
#1980000
b1000 (
b1100000 &
b1001011000000000 '
b10010110 !
b10010110 %
b1100001 #
b1100000 "
b1100000 $
#2000000
b1000 (
b1100001 &
b1001011100000000 '
b10010111 !
b10010111 %
b1100010 #
b1100001 "
b1100001 $
#2020000
b1000 (
b1100010 &
b1001100000000000 '
b10011000 !
b10011000 %
b1100011 #
b1100010 "
b1100010 $
#2040000
b1000 (
b1100011 &
b1001100100000000 '
b10011001 !
b10011001 %
b1100100 #
b1100011 "
b1100011 $
#2060000
b1000 (
b1100100 &
b0 '
b0 !
b0 %
b1100101 #
b1100100 "
b1100100 $
#2080000
b1000 (
b1100101 &
b100000000 '
b1 !
b1 %
b1100110 #
b1100101 "
b1100101 $
#2100000
b1000 (
b1100110 &
b1000000000 '
b10 !
b10 %
b1100111 #
b1100110 "
b1100110 $
#2120000
b1000 (
b1100111 &
b1100000000 '
b11 !
b11 %
b1101000 #
b1100111 "
b1100111 $
#2140000
b1000 (
b1101000 &
b10000000000 '
b100 !
b100 %
b1101001 #
b1101000 "
b1101000 $
#2160000
b1000 (
b1101001 &
b10100000000 '
b101 !
b101 %
b1101010 #
b1101001 "
b1101001 $
#2180000
b1000 (
b1101010 &
b11000000000 '
b110 !
b110 %
b1101011 #
b1101010 "
b1101010 $
#2200000
b1000 (
b1101011 &
b11100000000 '
b111 !
b111 %
b1101100 #
b1101011 "
b1101011 $
#2220000
b1000 (
b1101100 &
b100000000000 '
b1000 !
b1000 %
b1101101 #
b1101100 "
b1101100 $
#2240000
b1000 (
b1101101 &
b100100000000 '
b1001 !
b1001 %
b1101110 #
b1101101 "
b1101101 $
#2260000
b1000 (
b1101110 &
b1000000000000 '
b10000 !
b10000 %
b1101111 #
b1101110 "
b1101110 $
#2280000
b1000 (
b1101111 &
b1000100000000 '
b10001 !
b10001 %
b1110000 #
b1101111 "
b1101111 $
#2300000
b1000 (
b1110000 &
b1001000000000 '
b10010 !
b10010 %
b1110001 #
b1110000 "
b1110000 $
#2320000
b1000 (
b1110001 &
b1001100000000 '
b10011 !
b10011 %
b1110010 #
b1110001 "
b1110001 $
#2340000
b1000 (
b1110010 &
b1010000000000 '
b10100 !
b10100 %
b1110011 #
b1110010 "
b1110010 $
#2360000
b1000 (
b1110011 &
b1010100000000 '
b10101 !
b10101 %
b1110100 #
b1110011 "
b1110011 $
#2380000
b1000 (
b1110100 &
b1011000000000 '
b10110 !
b10110 %
b1110101 #
b1110100 "
b1110100 $
#2400000
b1000 (
b1110101 &
b1011100000000 '
b10111 !
b10111 %
b1110110 #
b1110101 "
b1110101 $
#2420000
b1000 (
b1110110 &
b1100000000000 '
b11000 !
b11000 %
b1110111 #
b1110110 "
b1110110 $
#2440000
b1000 (
b1110111 &
b1100100000000 '
b11001 !
b11001 %
b1111000 #
b1110111 "
b1110111 $
#2460000
b1000 (
b1111000 &
b10000000000000 '
b100000 !
b100000 %
b1111001 #
b1111000 "
b1111000 $
#2480000
b1000 (
b1111001 &
b10000100000000 '
b100001 !
b100001 %
b1111010 #
b1111001 "
b1111001 $
#2500000
b1000 (
b1111010 &
b10001000000000 '
b100010 !
b100010 %
b1111011 #
b1111010 "
b1111010 $
#2520000
b1000 (
b1111011 &
b10001100000000 '
b100011 !
b100011 %
b1111100 #
b1111011 "
b1111011 $
#2540000
b1000 (
b1111100 &
b10010000000000 '
b100100 !
b100100 %
b1111101 #
b1111100 "
b1111100 $
#2560000
b1000 (
b1111101 &
b10010100000000 '
b100101 !
b100101 %
b1111110 #
b1111101 "
b1111101 $
#2580000
b1000 (
b1111110 &
b10011000000000 '
b100110 !
b100110 %
b1111111 #
b1111110 "
b1111110 $
#2600000
b1000 (
b1111111 &
b10011100000000 '
b100111 !
b100111 %
b10000000 #
b1111111 "
b1111111 $
#2620000
b1000 (
b10000000 &
b10100000000000 '
b101000 !
b101000 %
b10000001 #
b10000000 "
b10000000 $
#2640000
b1000 (
b10000001 &
b10100100000000 '
b101001 !
b101001 %
b10000010 #
b10000001 "
b10000001 $
#2660000
b1000 (
b10000010 &
b11000000000000 '
b110000 !
b110000 %
b10000011 #
b10000010 "
b10000010 $
#2680000
b1000 (
b10000011 &
b11000100000000 '
b110001 !
b110001 %
b10000100 #
b10000011 "
b10000011 $
#2700000
b1000 (
b10000100 &
b11001000000000 '
b110010 !
b110010 %
b10000101 #
b10000100 "
b10000100 $
#2720000
b1000 (
b10000101 &
b11001100000000 '
b110011 !
b110011 %
b10000110 #
b10000101 "
b10000101 $
#2740000
b1000 (
b10000110 &
b11010000000000 '
b110100 !
b110100 %
b10000111 #
b10000110 "
b10000110 $
#2760000
b1000 (
b10000111 &
b11010100000000 '
b110101 !
b110101 %
b10001000 #
b10000111 "
b10000111 $
#2780000
b1000 (
b10001000 &
b11011000000000 '
b110110 !
b110110 %
b10001001 #
b10001000 "
b10001000 $
#2800000
b1000 (
b10001001 &
b11011100000000 '
b110111 !
b110111 %
b10001010 #
b10001001 "
b10001001 $
#2820000
b1000 (
b10001010 &
b11100000000000 '
b111000 !
b111000 %
b10001011 #
b10001010 "
b10001010 $
#2840000
b1000 (
b10001011 &
b11100100000000 '
b111001 !
b111001 %
b10001100 #
b10001011 "
b10001011 $
#2860000
b1000 (
b10001100 &
b100000000000000 '
b1000000 !
b1000000 %
b10001101 #
b10001100 "
b10001100 $
#2880000
b1000 (
b10001101 &
b100000100000000 '
b1000001 !
b1000001 %
b10001110 #
b10001101 "
b10001101 $
#2900000
b1000 (
b10001110 &
b100001000000000 '
b1000010 !
b1000010 %
b10001111 #
b10001110 "
b10001110 $
#2920000
b1000 (
b10001111 &
b100001100000000 '
b1000011 !
b1000011 %
b10010000 #
b10001111 "
b10001111 $
#2940000
b1000 (
b10010000 &
b100010000000000 '
b1000100 !
b1000100 %
b10010001 #
b10010000 "
b10010000 $
#2960000
b1000 (
b10010001 &
b100010100000000 '
b1000101 !
b1000101 %
b10010010 #
b10010001 "
b10010001 $
#2980000
b1000 (
b10010010 &
b100011000000000 '
b1000110 !
b1000110 %
b10010011 #
b10010010 "
b10010010 $
#3000000
b1000 (
b10010011 &
b100011100000000 '
b1000111 !
b1000111 %
b10010100 #
b10010011 "
b10010011 $
#3020000
b1000 (
b10010100 &
b100100000000000 '
b1001000 !
b1001000 %
b10010101 #
b10010100 "
b10010100 $
#3040000
b1000 (
b10010101 &
b100100100000000 '
b1001001 !
b1001001 %
b10010110 #
b10010101 "
b10010101 $
#3060000
b1000 (
b10010110 &
b101000000000000 '
b1010000 !
b1010000 %
b10010111 #
b10010110 "
b10010110 $
#3080000
b1000 (
b10010111 &
b101000100000000 '
b1010001 !
b1010001 %
b10011000 #
b10010111 "
b10010111 $
#3100000
b1000 (
b10011000 &
b101001000000000 '
b1010010 !
b1010010 %
b10011001 #
b10011000 "
b10011000 $
#3120000
b1000 (
b10011001 &
b101001100000000 '
b1010011 !
b1010011 %
b10011010 #
b10011001 "
b10011001 $
#3140000
b1000 (
b10011010 &
b101010000000000 '
b1010100 !
b1010100 %
b10011011 #
b10011010 "
b10011010 $
#3160000
b1000 (
b10011011 &
b101010100000000 '
b1010101 !
b1010101 %
b10011100 #
b10011011 "
b10011011 $
#3180000
b1000 (
b10011100 &
b101011000000000 '
b1010110 !
b1010110 %
b10011101 #
b10011100 "
b10011100 $
#3200000
b1000 (
b10011101 &
b101011100000000 '
b1010111 !
b1010111 %
b10011110 #
b10011101 "
b10011101 $
#3220000
b1000 (
b10011110 &
b101100000000000 '
b1011000 !
b1011000 %
b10011111 #
b10011110 "
b10011110 $
#3240000
b1000 (
b10011111 &
b101100100000000 '
b1011001 !
b1011001 %
b10100000 #
b10011111 "
b10011111 $
#3260000
b1000 (
b10100000 &
b110000000000000 '
b1100000 !
b1100000 %
b10100001 #
b10100000 "
b10100000 $
#3280000
b1000 (
b10100001 &
b110000100000000 '
b1100001 !
b1100001 %
b10100010 #
b10100001 "
b10100001 $
#3300000
b1000 (
b10100010 &
b110001000000000 '
b1100010 !
b1100010 %
b10100011 #
b10100010 "
b10100010 $
#3320000
b1000 (
b10100011 &
b110001100000000 '
b1100011 !
b1100011 %
b10100100 #
b10100011 "
b10100011 $
#3340000
b1000 (
b10100100 &
b110010000000000 '
b1100100 !
b1100100 %
b10100101 #
b10100100 "
b10100100 $
#3360000
b1000 (
b10100101 &
b110010100000000 '
b1100101 !
b1100101 %
b10100110 #
b10100101 "
b10100101 $
#3380000
b1000 (
b10100110 &
b110011000000000 '
b1100110 !
b1100110 %
b10100111 #
b10100110 "
b10100110 $
#3400000
b1000 (
b10100111 &
b110011100000000 '
b1100111 !
b1100111 %
b10101000 #
b10100111 "
b10100111 $
#3420000
b1000 (
b10101000 &
b110100000000000 '
b1101000 !
b1101000 %
b10101001 #
b10101000 "
b10101000 $
#3440000
b1000 (
b10101001 &
b110100100000000 '
b1101001 !
b1101001 %
b10101010 #
b10101001 "
b10101001 $
#3460000
b10101010 &
b10101010 !
b10101010 %
b10101011 #
b10101010 "
b10101010 $
#3480000
b1000 (
b10101011 &
b111000100000000 '
b1110001 !
b1110001 %
b10101100 #
b10101011 "
b10101011 $
#3500000
b1000 (
b10101100 &
b111001000000000 '
b1110010 !
b1110010 %
b10101101 #
b10101100 "
b10101100 $
#3520000
b1000 (
b10101101 &
b111001100000000 '
b1110011 !
b1110011 %
b10101110 #
b10101101 "
b10101101 $
#3540000
b1000 (
b10101110 &
b111010000000000 '
b1110100 !
b1110100 %
b10101111 #
b10101110 "
b10101110 $
#3560000
b1000 (
b10101111 &
b111010100000000 '
b1110101 !
b1110101 %
b10110000 #
b10101111 "
b10101111 $
#3580000
b1000 (
b10110000 &
b111011000000000 '
b1110110 !
b1110110 %
b10110001 #
b10110000 "
b10110000 $
#3600000
b1000 (
b10110001 &
b111011100000000 '
b1110111 !
b1110111 %
b10110010 #
b10110001 "
b10110001 $
#3620000
b1000 (
b10110010 &
b111100000000000 '
b1111000 !
b1111000 %
b10110011 #
b10110010 "
b10110010 $
#3640000
b1000 (
b10110011 &
b111100100000000 '
b1111001 !
b1111001 %
b10110100 #
b10110011 "
b10110011 $
#3660000
b1000 (
b10110100 &
b1000000000000000 '
b10000000 !
b10000000 %
b10110101 #
b10110100 "
b10110100 $
#3680000
b1000 (
b10110101 &
b1000000100000000 '
b10000001 !
b10000001 %
b10110110 #
b10110101 "
b10110101 $
#3700000
b1000 (
b10110110 &
b1000001000000000 '
b10000010 !
b10000010 %
b10110111 #
b10110110 "
b10110110 $
#3720000
b1000 (
b10110111 &
b1000001100000000 '
b10000011 !
b10000011 %
b10111000 #
b10110111 "
b10110111 $
#3740000
b1000 (
b10111000 &
b1000010000000000 '
b10000100 !
b10000100 %
b10111001 #
b10111000 "
b10111000 $
#3760000
b1000 (
b10111001 &
b1000010100000000 '
b10000101 !
b10000101 %
b10111010 #
b10111001 "
b10111001 $
#3780000
b1000 (
b10111010 &
b1000011000000000 '
b10000110 !
b10000110 %
b10111011 #
b10111010 "
b10111010 $
#3800000
b1000 (
b10111011 &
b1000011100000000 '
b10000111 !
b10000111 %
b10111100 #
b10111011 "
b10111011 $
#3820000
b1000 (
b10111100 &
b1000100000000000 '
b10001000 !
b10001000 %
b10111101 #
b10111100 "
b10111100 $
#3840000
b1000 (
b10111101 &
b1000100100000000 '
b10001001 !
b10001001 %
b10111110 #
b10111101 "
b10111101 $
#3860000
b1000 (
b10111110 &
b1001000000000000 '
b10010000 !
b10010000 %
b10111111 #
b10111110 "
b10111110 $
#3880000
b1000 (
b10111111 &
b1001000100000000 '
b10010001 !
b10010001 %
b11000000 #
b10111111 "
b10111111 $
#3900000
b1000 (
b11000000 &
b1001001000000000 '
b10010010 !
b10010010 %
b11000001 #
b11000000 "
b11000000 $
#3920000
b1000 (
b11000001 &
b1001001100000000 '
b10010011 !
b10010011 %
b11000010 #
b11000001 "
b11000001 $
#3940000
b1000 (
b11000010 &
b1001010000000000 '
b10010100 !
b10010100 %
b11000011 #
b11000010 "
b11000010 $
#3960000
b1000 (
b11000011 &
b1001010100000000 '
b10010101 !
b10010101 %
b11000100 #
b11000011 "
b11000011 $
#3980000
b1000 (
b11000100 &
b1001011000000000 '
b10010110 !
b10010110 %
b11000101 #
b11000100 "
b11000100 $
#4000000
b1000 (
b11000101 &
b1001011100000000 '
b10010111 !
b10010111 %
b11000110 #
b11000101 "
b11000101 $
#4020000
b1000 (
b11000110 &
b1001100000000000 '
b10011000 !
b10011000 %
b11000111 #
b11000110 "
b11000110 $
#4040000
b1000 (
b11000111 &
b1001100100000000 '
b10011001 !
b10011001 %
b11001000 #
b11000111 "
b11000111 $
#4060000
b1000 (
b11001000 &
b0 '
b0 !
b0 %
b11001001 #
b11001000 "
b11001000 $
#4080000
b1000 (
b11001001 &
b100000000 '
b1 !
b1 %
b11001010 #
b11001001 "
b11001001 $
#4100000
b1000 (
b11001010 &
b1000000000 '
b10 !
b10 %
b11001011 #
b11001010 "
b11001010 $
#4120000
b1000 (
b11001011 &
b1100000000 '
b11 !
b11 %
b11001100 #
b11001011 "
b11001011 $
#4140000
b1000 (
b11001100 &
b10000000000 '
b100 !
b100 %
b11001101 #
b11001100 "
b11001100 $
#4160000
b1000 (
b11001101 &
b10100000000 '
b101 !
b101 %
b11001110 #
b11001101 "
b11001101 $
#4180000
b1000 (
b11001110 &
b11000000000 '
b110 !
b110 %
b11001111 #
b11001110 "
b11001110 $
#4200000
b1000 (
b11001111 &
b11100000000 '
b111 !
b111 %
b11010000 #
b11001111 "
b11001111 $
#4220000
b1000 (
b11010000 &
b100000000000 '
b1000 !
b1000 %
b11010001 #
b11010000 "
b11010000 $
#4240000
b1000 (
b11010001 &
b100100000000 '
b1001 !
b1001 %
b11010010 #
b11010001 "
b11010001 $
#4260000
b1000 (
b11010010 &
b1000000000000 '
b10000 !
b10000 %
b11010011 #
b11010010 "
b11010010 $
#4280000
b1000 (
b11010011 &
b1000100000000 '
b10001 !
b10001 %
b11010100 #
b11010011 "
b11010011 $
#4300000
b1000 (
b11010100 &
b1001000000000 '
b10010 !
b10010 %
b11010101 #
b11010100 "
b11010100 $
#4320000
b1000 (
b11010101 &
b1001100000000 '
b10011 !
b10011 %
b11010110 #
b11010101 "
b11010101 $
#4340000
b1000 (
b11010110 &
b1010000000000 '
b10100 !
b10100 %
b11010111 #
b11010110 "
b11010110 $
#4360000
b1000 (
b11010111 &
b1010100000000 '
b10101 !
b10101 %
b11011000 #
b11010111 "
b11010111 $
#4380000
b1000 (
b11011000 &
b1011000000000 '
b10110 !
b10110 %
b11011001 #
b11011000 "
b11011000 $
#4400000
b1000 (
b11011001 &
b1011100000000 '
b10111 !
b10111 %
b11011010 #
b11011001 "
b11011001 $
#4420000
b1000 (
b11011010 &
b1100000000000 '
b11000 !
b11000 %
b11011011 #
b11011010 "
b11011010 $
#4440000
b1000 (
b11011011 &
b1100100000000 '
b11001 !
b11001 %
b11011100 #
b11011011 "
b11011011 $
#4460000
b1000 (
b11011100 &
b10000000000000 '
b100000 !
b100000 %
b11011101 #
b11011100 "
b11011100 $
#4480000
b1000 (
b11011101 &
b10000100000000 '
b100001 !
b100001 %
b11011110 #
b11011101 "
b11011101 $
#4500000
b1000 (
b11011110 &
b10001000000000 '
b100010 !
b100010 %
b11011111 #
b11011110 "
b11011110 $
#4520000
b1000 (
b11011111 &
b10001100000000 '
b100011 !
b100011 %
b11100000 #
b11011111 "
b11011111 $
#4540000
b1000 (
b11100000 &
b10010000000000 '
b100100 !
b100100 %
b11100001 #
b11100000 "
b11100000 $
#4560000
b1000 (
b11100001 &
b10010100000000 '
b100101 !
b100101 %
b11100010 #
b11100001 "
b11100001 $
#4580000
b1000 (
b11100010 &
b10011000000000 '
b100110 !
b100110 %
b11100011 #
b11100010 "
b11100010 $
#4600000
b1000 (
b11100011 &
b10011100000000 '
b100111 !
b100111 %
b11100100 #
b11100011 "
b11100011 $
#4620000
b1000 (
b11100100 &
b10100000000000 '
b101000 !
b101000 %
b11100101 #
b11100100 "
b11100100 $
#4640000
b1000 (
b11100101 &
b10100100000000 '
b101001 !
b101001 %
b11100110 #
b11100101 "
b11100101 $
#4660000
b1000 (
b11100110 &
b11000000000000 '
b110000 !
b110000 %
b11100111 #
b11100110 "
b11100110 $
#4680000
b1000 (
b11100111 &
b11000100000000 '
b110001 !
b110001 %
b11101000 #
b11100111 "
b11100111 $
#4700000
b1000 (
b11101000 &
b11001000000000 '
b110010 !
b110010 %
b11101001 #
b11101000 "
b11101000 $
